elasticbackup/__init__.py
elasticbackup/backup.py
elasticbackup/restore.py
elasticbackup-0.4.0.dist-info/DESCRIPTION.rst
elasticbackup-0.4.0.dist-info/METADATA
elasticbackup-0.4.0.dist-info/RECORD
elasticbackup-0.4.0.dist-info/WHEEL
elasticbackup-0.4.0.dist-info/entry_points.txt
elasticbackup-0.4.0.dist-info/metadata.json
elasticbackup-0.4.0.dist-info/top_level.txt
