Metadata-Version: 2.0
Name: elasticbackup
Version: 0.4.0
Summary: elasticbackup: tools to backup and restore ElasticSearch indices
Home-page: https://github.com/nickstenning/elasticbackup
Author: Nick Stenning
Author-email: nick@whiteink.com
License: MIT
Keywords: sysadmin elasticsearch backup restore
Platform: UNKNOWN
Requires-Dist: elasticsearch (>=1.0.0,<1.1.0)
